esi_utils_cartopy/mercatormap.py
esi_utils_cartopy/scalebar.py
esi_utils_cartopy-0.1.2.dist-info/METADATA
esi_utils_cartopy-0.1.2.dist-info/WHEEL
esi_utils_cartopy-0.1.2.dist-info/top_level.txt
esi_utils_cartopy-0.1.2.dist-info/RECORD
