Metadata-Version: 2.4
Name: esi-utils-cartopy
Version: 0.1.2
Summary: USGS Earthquake Basic Geographic Utilities
Author-email: Mike Hearne <mhearne@usgs.gov>
Keywords: utilities,cartopy
Requires-Python: >=3.8
Requires-Dist: cartopy
Requires-Dist: esi_utils_geo>=0.9.0
Requires-Dist: matplotlib
Requires-Dist: numpy
Requires-Dist: pyproj
Provides-Extra: dev
Requires-Dist: build>=0.7.0; extra == "dev"
Requires-Dist: black>=21; extra == "dev"
Requires-Dist: flake8>=3.9; extra == "dev"
Requires-Dist: ipython>=7.26; extra == "dev"
Provides-Extra: test
Requires-Dist: pytest>=6.2; extra == "test"
Requires-Dist: pytest-cov>=2.12.0; extra == "test"
Provides-Extra: build
Requires-Dist: build; extra == "build"
Requires-Dist: twine; extra == "build"
Requires-Dist: check-wheel-contents; extra == "build"
